{
    "data":
    [
        "sysLoadPwr",
        "sysGridPwr",
        "mpptPwr",
        "bpPwr",
        "bpSoc",
        "online",
        "systemName",
        "createTime",
        "location",
        "timezone"
	],
	"JTS1_EMS_CHANGE_REPORT": 
	[
    ],
	"JTS1_BP_STA_REPORT":
	[
    ],
	"JTS1_ENERGY_STREAM_REPORT": 
	[
		"bpSoc",
		"heatingPower",
		"dcdcPwr",
		"bpPwr",
		"pvPwr",
		"gridPwr",
		"loadPwr",
		"timezone",
		"updateTime",
		"timestamp"
    ],
	"JTS1_EMS_HEARTBEAT": 
	[
		"emsSystemState",
		"mpptRatePower",
		"gridOutDayEnergy",
		"meterACurrent",
		"meterBCurrent",
		"bpInDayEnergy",
		"meterPowerFactor",
		"isPvToInvDirectly",
		"bpRemainWatth",
		"bp1SocCoefficient",
		"sysRunMeterFeedPower",
		"inverterBand",
		"loadDayEnergy",
		"startDischargePower",
		"bpDichargeAbilityAdjustValueLv2",
		"bpDichargeAbilityAdjustValueLv1",
		"meterAddress",
		"gridFeedRate",
		"currentNetif",
		"batterySocLowerLimit",
		"bpDsgTime",
		"bpChgDsgSta",
		"autoDetectStartPowerEn",
		"meterPhasePower",
		"sysErrCode",
		"meterTotalPower",
		"bpBusVoltageBaseCoefficient",
		"bpSaveSocStopDelay",
		"bpOutDayEnergy",
		"bpBusVoltCoefficient",
		"pvInvWiringMode",
		"underVoltageProtectPoint",
		"batterySocUpperLimit",
		"bpRunDelay",
		"meterBVoltage",
		"bpStopDelay",
		"errCode",
		"gridInDayEnergy",
		"sysRunMeterTakePower",
		"bpSoc",
		"bp3SocCoefficient",
		"bpErrorCodeMask",
		"workingMode",
		"appCtrlState",
		"bpSocBaseCoefficient",
		"emsErrorCodeMask",
		"meterRatio",
		"sysWorkSta",
		"pv2ErrorCodeMask",
		"pv1ErrorCodeMask",
		"manualSetStartChargePower",
		"pvWiringType",
		"emsErrCode",
		"bp2SocCoefficient",
		"mpptWithstandVoltage",
		"meterCVoltage",
		"updateTime",
		"pvaErrorCodeMask",
		"meterAVoltage",
		"invWiringType",
		"disOrChargeAbilityStepValue",
		"reportCycleTime",
		"pvInDayEnergy",
		"meterType",
		"meterCCurrent",
		"mpptVoltageMinimum",
		"mpptVoltageMaximum",
		"gridFeedPowerMinimum",
		"epoSwitchState"
	]
}